LICENSE
MANIFEST.in
README.md
setup.py
tap_saasoptics/__init__.py
tap_saasoptics/client.py
tap_saasoptics/discover.py
tap_saasoptics/schema.py
tap_saasoptics/streams.py
tap_saasoptics/sync.py
tap_saasoptics/transform.py
tap_saasoptics.egg-info/PKG-INFO
tap_saasoptics.egg-info/SOURCES.txt
tap_saasoptics.egg-info/dependency_links.txt
tap_saasoptics.egg-info/entry_points.txt
tap_saasoptics.egg-info/requires.txt
tap_saasoptics.egg-info/top_level.txt
tap_saasoptics/schemas/accounts.json
tap_saasoptics/schemas/auto_renewal_profiles.json
tap_saasoptics/schemas/billing_descriptions.json
tap_saasoptics/schemas/billing_methods.json
tap_saasoptics/schemas/contracts.json
tap_saasoptics/schemas/country_codes.json
tap_saasoptics/schemas/currency_codes.json
tap_saasoptics/schemas/customers.json
tap_saasoptics/schemas/deleted_contracts.json
tap_saasoptics/schemas/deleted_invoices.json
tap_saasoptics/schemas/deleted_revenue_entries.json
tap_saasoptics/schemas/deleted_transactions.json
tap_saasoptics/schemas/invoices.json
tap_saasoptics/schemas/items.json
tap_saasoptics/schemas/payment_terms.json
tap_saasoptics/schemas/registers.json
tap_saasoptics/schemas/revenue_entries.json
tap_saasoptics/schemas/revenue_recognition_methods.json
tap_saasoptics/schemas/sales_orders.json
tap_saasoptics/schemas/transactions.json