Metadata-Version: 1.1
Name: tap-saasoptics
Version: 1.1.1
Summary: Singer.io tap for extracting data from the SaaSOptics v1.0 API
Home-page: UNKNOWN
Author: jeff.huth@bytecode.io
Author-email: UNKNOWN
License: UNKNOWN
Platform: UNKNOWN
Classifier: Programming Language :: Python :: 3 :: Only
